twitchdetox/__init__.py
twitchdetox/bot.py
twitchdetox/files_to_copy.json
twitchdetox/get_user_info.py
twitchdetox/settings.py
twitchdetox-0.0.4.dist-info/entry_points.txt
twitchdetox-0.0.4.dist-info/LICENSE
twitchdetox-0.0.4.dist-info/WHEEL
twitchdetox-0.0.4.dist-info/METADATA
twitchdetox-0.0.4.dist-info/RECORD
